googlelogin/__init__.py
googlelogin/googlelogin.py
googlelogin/selenium.py
scrapy_googlelogin-0.1.7.dist-info/METADATA
scrapy_googlelogin-0.1.7.dist-info/WHEEL
scrapy_googlelogin-0.1.7.dist-info/top_level.txt
scrapy_googlelogin-0.1.7.dist-info/RECORD
