Metadata-Version: 2.4
Name: scrapy-googlelogin
Version: 0.1.7
Summary: google login downloader middleware for scrapy
Home-page: https://github.com/geek-dc/scrapy-googlelogin
Author: derekchan
Author-email: dchan0831@gmail.com
License: MIT Licence
Keywords: pip,datacanvas,eds,xiaoh
Platform: any
Requires-Dist: selenium
Requires-Dist: pyotp
Dynamic: author
Dynamic: author-email
Dynamic: description
Dynamic: home-page
Dynamic: keywords
Dynamic: license
Dynamic: platform
Dynamic: requires-dist
Dynamic: summary
